<?xml version="1.0"?>
<files>
  <file name="aiprofiles.html" />
  <file name="background.jpg" />
  <file name="championship.html" />
  <file name="favicon.ico" />
  <file name="index.html" />
  <file name="jquery-ui.css" />
  <file name="jquery-ui.min.css" />
  <file name="jquery-ui.min.js" />
  <file name="jquery-ui.structure.css" />
  <file name="jquery-ui.structure.min.css" />
  <file name="jquery-ui.theme.css" />
  <file name="jquery-ui.theme.min.css" />
  <file name="jquery.ddslick.min.js" />
  <file name="jquery.js" />
  <file name="jquery.treemenu.min.css" />
  <file name="jquery.treemenu.min.js" />
  <file name="marblegp_logo.png" />
  <file name="profiles.html" />
  <file name="texturedialog.css" />
  <file name="texturedialog.html" />
  <file name="texturedialog.js" />
  <file name="texturerenderer.js" />
</files>
